dqu/__init__.py
dqu/base.py
dqu/config_runner.py
dqu/kernel/__init__.py
dqu/kernel/dataframe.py
dqu/kernel/engine_runner.py
dqu/kernel/engine/__init__.py
dqu/kernel/engine/base_engine.py
dqu/kernel/engine/flink_engine.py
dqu/kernel/engine/pandas_engine.py
dqu/kernel/engine/ray_engine.py
dqu/kernel/engine/spark_engine.py
dqu/log/__init__.py
dqu/log/logger.py
dqu/utils/__init__.py
dqu/utils/config_validator.py
dqu/utils/exceptions.py
dqu/utils/time_utils.py
dqu/validators/__init__.py
dqu/validators/categoricalvalues_check.py
dqu/validators/custom_check.py
dqu/validators/datafreshness_check.py
dqu/validators/dtype_check.py
dqu/validators/dup_check.py
dqu/validators/empty_check.py
dqu/validators/range_check.py
dqu/validators/referential_integrity_check.py
dqu/validators/rowcount_check.py
dqu/validators/schema_check.py
dqu/validators/statisticaldistribution_check.py
dqu/validators/stringformat_check.py
dqu/validators/unique_check.py
dqu-0.2.5.dist-info/LICENSE
dqu-0.2.5.dist-info/METADATA
dqu-0.2.5.dist-info/WHEEL
dqu-0.2.5.dist-info/top_level.txt
dqu-0.2.5.dist-info/RECORD
