Metadata-Version: 2.1
Name: dqu
Version: 0.2.5
Summary: Build intelligent, efficient, and trustable Data & ML Engineering Pipelines with this enterprise-ready Data Quality framework.
Author: Keshav Kant Singh
Author-email: Keshav Singh <masterkeshav@gmail.com>
Classifier: Programming Language :: Python :: 3
Classifier: License :: OSI Approved :: MIT License
Classifier: Operating System :: OS Independent
Requires-Python: >=3.7
License-File: LICENSE
